ppa_api/__init__.py
ppa_api/_client.py
ppa_api/client.py
ppa_api/create.py
ppa_api/exceptions.py
ppa_api/models.py
ppa_api-2.7.0.dist-info/LICENSE
ppa_api-2.7.0.dist-info/METADATA
ppa_api-2.7.0.dist-info/WHEEL
ppa_api-2.7.0.dist-info/top_level.txt
ppa_api-2.7.0.dist-info/RECORD
